{
  "challenge_uid": "a078935e-443c-4aed-bd89-5f41852d6cef",
  "language": "en",
  "dialogues": [
    {
      "dialogue_uid": "1dd42518-5ab7-4f93-8769-4eeaf6d32ec2",
      "language": "en",
      "utterances": [
        "(Singing) Lost hours and secrets too.",
        "No one will find but you.",
        "Falling is like brand new rain, Places I have never been.",
        "I thought these things would come to me.",
        "Love is another country, and I want to go.",
        "I want to go, too.",
        "I want to go with you.",
        "I want to go with you.",
        "But I'm broke down right here.",
        "My heart won't come out clear.",
        "I get lost on the inside, too.",
        "How could I make sense to you?",
        "And when you walk away from me, you're further than another country, and I want to go.",
        "I want to go, too.",
        "I want to go with you.",
        "I want to go, too.",
        "I want to go with you.",
        "I want to go with you.",
        "The barbershop needs so many heads to cut.",
        "The grocery store needs so many customers.",
        "All of the various businesses up and down Broadway feel this immensely.",
        "If you should lose you place, this world should hide its face.",
        "And go where you can't follow to, I will come and look for you.",
        "And you can just hold onto me, Strangers in another country.",
        "Cause I want to go.",
        "I want to go, too.",
        "I want to go with you.",
        "I want to go, too.",
        "I want to go with you.",
        "I want to go with you.",
        "I want to go with you.",
        "(Soundbite of cheers and applause)",
        "Another Country,\"\" the title track of Tift Merritt's new album and she's with us here today in Studio 4A.",
        "Let's see if we can get a caller on the line.",
        "And let's go to - oops, I have to hit the right computer, that would help.",
        "This is Marty(ph).",
        "Marty with us from Farley, what state is Farley in?",
        "Yes, hi there.",
        "Hi.",
        "What - Farley?",
        "What state is that?",
        "Oh, that's in the state of Iowa."
      ]
    },
    {
      "dialogue_uid": "cb09ba76-d4e6-4d54-8ebb-3232fc2e751d",
      "language": "en",
      "utterances": [
        "Iowa.",
        "Okay.",
        "Go ahead, I'm sure is not it's not that little town with 50 people in the - well, never mind.",
        "(Soundbite of laughter)",
        "Yeah, that's about of how many people are in my town, I swear.",
        "(Soundbite of laughter)",
        "What you got?",
        "She got everybody then.",
        "Go ahead.",
        "(Soundbite of laughter)",
        "Yeah.",
        "No, I was just - I'm being introduced to your music.",
        "And I was just knocked out by that first song.",
        "And I'm an aspiring writer myself.",
        "Oh.",
        "And I just - I'm always kind of interested in finding out, you know, creative processes…",
        "Sure."
      ]
    },
    {
      "dialogue_uid": "52d12da2-b583-4d68-8ca2-9dc8bf608238",
      "language": "en",
      "utterances": [
        "…that various writers use.",
        "And without showing your cards too much, I think I just…",
        "No, no. I'm happy to show my cards.",
        "(Soundbite of laughter)",
        "Yeah.",
        "I'm just…",
        "It's a job.",
        "(Soundbite of laughter)",
        "I'm just curious, I have - since I started writing songs, I also got into - deep into classic literature and reading…",
        "Hmm.",
        "…heavily.",
        "And I don't know if that's the right process or not.",
        "But your songs are well written…",
        "Thank you."
      ]
    },
    {
      "dialogue_uid": "ff17498e-b9f9-4e65-8b58-60fb6ab7e3c2",
      "language": "en",
      "utterances": [
        "…and your voice is exquisite.",
        "I mean, it's this beautiful voice on top of all of it.",
        "Wow, you're such a nice caller.",
        "Just kind of curious what your creative processed may be.",
        "Well, I - you know, it's funny because when I am in a creative time, I like to be isolated.",
        "You know, I like to not be fettered by some calls and e-mails and errands and that sort of thing.",
        "And I do end up reading and writing prose and just telling a story in as many ways that I can.",
        "I find that if things are working and if I'm actually working on a good song and it's going well, that the music and the lyrics are married and they never - one never gets too far ahead of the other.",
        "So I might find the structure for the verse and the chorus and lay that out a little bit earlier than the lyrics is finished, but it never becomes, oh, I have this great tune, I wonder what words I'll put with it.",
        "Or I have this word I wonder what the melody would be?",
        "It's something that starts together and that's usually how I know that I should keep going.",
        "Does that help at all?",
        "That helps out tremendously because I often thought about writing prose, as well, and then picking up ideas out of that.",
        "I understand Bob Dylan wrote a lot by using that technique.",
        "He definitely wrote a lot, didn't he?",
        "(Soundbite of laughter)",
        "Right.",
        "But no, that's fabulous and I am delighted to talk you.",
        "I'm going to drive to Borders this afternoon and see if I can find a copy of your music.",
        "You're the best.",
        "Thank you so much.",
        "Good luck with your writing."
      ]
    },
    {
      "dialogue_uid": "baeedf65-ae72-4711-8e3c-ba223ff165d9",
      "language": "en",
      "utterances": [
        "Thank you.",
        "God bless you.",
        "Bye-bye.",
        "Thanks with the call, Marty.",
        "We have a question here in the studio audience.",
        "Oh, well, it's Jackie Northam.",
        "I'm one of the reporters here at NPR.",
        "I just wondered, you were talking about how you were disillusioned after you are dropped from your label, and that you went to the best place on Earth to regroup - Paris, and that type of thing.",
        "How long did it take for you to - actually to regroup?",
        "And, also, was it a gradual kind of re-enchantment with your art, your music again?",
        "Or was it - that one defining moment we just talked, that this is what I have to do?",
        "Well, it's funny; I actually was dropped when I came back from Paris with this new record.",
        "Oh.",
        "(Soundbite of laughter)",
        "Which ended up being fine.",
        "I mean, you know, it's all fine.",
        "I'm not a bitter, disenchanted person.",
        "But I was at the point where I was really tired.",
        "And I think what happened was, when I was in Paris I was able to wake up in one city over and over, which helped a lot.",
        "And then I had this apartment with a piano in it and I loved to play the piano.",
        "And I didn't have any designs on anything, you know, but I just started to write and I was such a surprise, it was such a surprise.",
        "And…",
        "But did that - excuse me.",
        "(Soundbite of laughter)"
      ]
    }
  ]
}